maked/__init.py__
maked/main.py
maked-0.1.0.dist-info/LICENSE
maked-0.1.0.dist-info/METADATA
maked-0.1.0.dist-info/WHEEL
maked-0.1.0.dist-info/entry_points.txt
maked-0.1.0.dist-info/RECORD
