Metadata-Version: 2.3
Name: maked
Version: 0.1.0
Summary: A CLI tool to execute commands inside Markdown files
License: MIT
Author: Luis Cruz
Author-email: luismirandacruz@gmail.com
Requires-Python: >=3.13
Classifier: License :: OSI Approved :: MIT License
Classifier: Programming Language :: Python :: 3
Classifier: Programming Language :: Python :: 3.13
Requires-Dist: click (>=8.1.8,<9.0.0)
Requires-Dist: pyyaml (>=6.0.2,<7.0.0)
